{"@context":"\/contexts\/Tournament","@id":"\/tournaments\/8376","@type":"Tournament","id":8376,"name":"Мюнхен зовёт (асинхрон)","lastEditDate":"2022-09-11T20:26:00+03:00","dateStart":"2022-09-02T10:00:00+03:00","dateEnd":"2022-10-02T23:55:00+03:00","type":{"@id":"\/tournament_types\/8","@type":"TournamentType","id":8,"name":"Асинхрон"},"season":"\/seasons\/57","orgcommittee":[{"@id":"\/players\/21375","@type":"Player","id":21375,"name":"Максим","patronymic":"Леонидович","surname":"Мозуль"}],"synchData":{"@id":"\/tournament_synches\/8376","@type":"TournamentSynch","dateRequestsAllowedTo":"2022-10-02T23:55:00+03:00","resultFixesTo":"2022-10-09T23:55:00+03:00","resultsRecapsTo":"2022-10-07T23:55:00+03:00","allowAppealCancel":true,"allowNarratorErrorAppeal":false,"archive":false,"dateDownloadQuestionsFrom":"2022-08-31T00:00:00+03:00","dateDownloadQuestionsTo":"2022-09-25T20:30:00+03:00","hideQuestionsTo":"2022-10-02T23:55:00+03:00","hideResultsTo":"2022-10-02T23:55:00+03:00","instantControversial":true},"mainPayment":6,"discountedPaymentReason":"","currency":"e","editors":[{"@id":"\/players\/21375","@type":"Player","id":21375,"name":"Максим","patronymic":"Леонидович","surname":"Мозуль"},{"@id":"\/players\/10293","@type":"Player","id":10293,"name":"Михаил","patronymic":"Сергеевич","surname":"Екимов"}],"tournamentInRatingBalanced":false,"difficultyForecast":4,"maiiAegis":true,"maiiAegisUpdatedAt":"2022-08-31T22:10:59.521097Z","maiiRating":false,"questionQty":{"1":12,"2":12,"3":12}}